dynamicinputbox/__init__.py
dynamicinputbox/dynamicinputbox.py
dynamicinputbox-1.3.1.dist-info/METADATA
dynamicinputbox-1.3.1.dist-info/WHEEL
dynamicinputbox-1.3.1.dist-info/top_level.txt
dynamicinputbox-1.3.1.dist-info/RECORD
